pushover_ml/GUI.py
pushover_ml/__init__.py
pushover_ml/Helpers/Draws.py
pushover_ml/Helpers/Press_Button.py
pushover_ml/Helpers/Requirements_Individual.py
pushover_ml/Helpers/Requirements_Multiple.py
pushover_ml/Helpers/SCWB_requirement.py
pushover_ml/Helpers/__init__.py
pushover_ml/Models/ANN_Fin_D.h5
pushover_ml/Models/ANN_Fin_Vs.h5
pushover_ml/Models/ANN_Max_D.h5
pushover_ml/Models/ANN_Max_Vs.h5
pushover_ml/Models/ANN_Plas_D.h5
pushover_ml/Models/ANN_Plas_Vs.h5
pushover_ml/Models/GBM_Fin_D.pkl
pushover_ml/Models/GBM_Fin_Vs.pkl
pushover_ml/Models/GBM_Max_D.pkl
pushover_ml/Models/GBM_Max_Vs.pkl
pushover_ml/Models/GBM_Plas_D.pkl
pushover_ml/Models/GBM_Plas_Vs.pkl
pushover_ml/Models/LASSO_Fin_D.pkl
pushover_ml/Models/LASSO_Fin_Vs.pkl
pushover_ml/Models/LASSO_Max_D.pkl
pushover_ml/Models/LASSO_Max_Vs.pkl
pushover_ml/Models/LASSO_Plas_D.pkl
pushover_ml/Models/LASSO_Plas_Vs.pkl
pushover_ml/Models/RF_Fin_D.pkl
pushover_ml/Models/RF_Fin_Vs.pkl
pushover_ml/Models/RF_Max_D.pkl
pushover_ml/Models/RF_Max_Vs.pkl
pushover_ml/Models/RF_Plas_D.pkl
pushover_ml/Models/RF_Plas_Vs.pkl
pushover_ml/Models/__init__.py
pushover_ml/Scalers/__init__.py
pushover_ml/Scalers/scalerX.pkl
pushover_ml/Scalers/scalerY_Fin_D.pkl
pushover_ml/Scalers/scalerY_Fin_Vs.pkl
pushover_ml/Scalers/scalerY_Max_D.pkl
pushover_ml/Scalers/scalerY_Max_Vs.pkl
pushover_ml/Scalers/scalerY_Plas_D.pkl
pushover_ml/Scalers/scalerY_Plas_Vs.pkl
pushover_ml-1.4.4.dist-info/METADATA
pushover_ml-1.4.4.dist-info/WHEEL
pushover_ml-1.4.4.dist-info/entry_points.txt
pushover_ml-1.4.4.dist-info/top_level.txt
pushover_ml-1.4.4.dist-info/RECORD
