Metadata-Version: 2.1
Name: pushover-ml
Version: 1.4.4
Summary: User-friendly Graphical User Interface (GUI) to efficiently predict a trilinear approximation of pushover curves for low-rise reinforced concrete (RC) frame buildings, using a Machine Learning (ML) based approach.
Home-page: https://github.com/carlosantr/Pushover-ML_repository
Author: Carlos Angarita
Author-email: carlosantr@unisabana.edu.co
License: Apache-2.0
Requires-Python: >=3.9
Requires-Dist: matplotlib >=3.9.1
Requires-Dist: numpy >=1.26.4
Requires-Dist: joblib >=1.4.2
Requires-Dist: scikit-learn ==1.2.1
Requires-Dist: tensorflow ==2.17.0
Requires-Dist: keras >=3.4.1
Requires-Dist: openpyxl >=3.1.5
Requires-Dist: Xlsxwriter >=3.2.0
Requires-Dist: pandas >=2.2.2
